[
  {
    "userDetails": {
      "id": 1,
      "fname": "Alice",
      "sname": "Smith",
      "loginDetails": {
        "email": "alice@example.com",
        "username": "alice123",
        "password": "password"
      }
    },
    "roles": [
      "petowner"
    ],
    "currentRole": "petowner",
    "primaryUserInfo": {
      "profilePic": "",
      "dob": "1990-06-15T00:00:00.000Z",
      "location": {
        "name": "Bristol",
        "longitude": -2.5879,
        "latitude": 51.4545
      },
      "suspended": false,
      "suspendReason": null,
      "suspendEndsAt": null
    },
    "ownerRoleInfo": {
      "petIDs": [
        3
      ],
      "bookingIDs": []
    },
    "minderRoleInfo": {
      "rating": 0,
      "bio": "",
      "pictures": [],
      "availability": "",
      "distanceRange": 0,
      "verified": false,
      "serviceIDs": [],
      "bookingIDs": []
    }
  },
  {
    "userDetails": {
      "id": 2,
      "fname": "Bob",
      "sname": "Johnson",
      "loginDetails": {
        "email": "bob@example.com",
        "username": "bobbyJ",
        "password": "password"
      }
    },
    "roles": [
      "petowner"
    ],
    "currentRole": "petowner",
    "primaryUserInfo": {
      "profilePic": "",
      "dob": "1985-09-20T00:00:00.000Z",
      "location": {
        "name": "Leeds",
        "longitude": -1.5491,
        "latitude": 53.8008
      },
      "suspended": false,
      "suspendReason": null,
      "suspendEndsAt": null
    },
    "ownerRoleInfo": {
      "petIDs": [
        4
      ],
      "bookingIDs": []
    },
    "minderRoleInfo": {
      "rating": 0,
      "bio": "",
      "pictures": [],
      "availability": "",
      "distanceRange": 0,
      "verified": false,
      "serviceIDs": [],
      "bookingIDs": []
    }
  },
  {
    "userDetails": {
      "id": 3,
      "fname": "Charlie",
      "sname": "Davis",
      "loginDetails": {
        "email": "charlie@example.com",
        "username": "charlieD",
        "password": "password"
      }
    },
    "roles": [
      "petminder",
      "petowner"
    ],
    "currentRole": "petminder",
    "primaryUserInfo": {
      "profilePic": "",
      "dob": "1992-04-10T00:00:00.000Z",
      "location": {
        "name": "Manchester",
        "longitude": -2.2426,
        "latitude": 53.4808
      },
      "suspended": false,
      "suspendReason": null,
      "suspendEndsAt": null
    },
    "ownerRoleInfo": {
      "petIDs": [],
      "bookingIDs": []
    },
    "minderRoleInfo": {
      "rating": 4.8,
      "bio": "Experienced pet sitter with 5 years of experience.",
      "pictures": [],
      "availability": "Weekdays",
      "distanceRange": 10,
      "verified": true,
      "serviceIDs": [
        1,
        2
      ],
      "bookingIDs": [
        1,
        2,
        3
      ]
    }
  },
  {
    "userDetails": {
      "id": 4,
      "fname": "Diana",
      "sname": "Evans",
      "loginDetails": {
        "email": "diana@example.com",
        "username": "dianaE",
        "password": "password"
      }
    },
    "roles": [
      "petminder"
    ],
    "currentRole": "petminder",
    "primaryUserInfo": {
      "profilePic": "",
      "dob": "1988-12-05T00:00:00.000Z",
      "location": {
        "name": "Brighton",
        "longitude": -0.1372,
        "latitude": 50.8225
      },
      "suspended": false,
      "suspendReason": null,
      "suspendEndsAt": null
    },
    "ownerRoleInfo": {
      "petIDs": [],
      "bookingIDs": []
    },
    "minderRoleInfo": {
      "rating": 4.6,
      "bio": "Lifelong pet lover and certified dog trainer.",
      "pictures": [],
      "availability": "Weekends",
      "distanceRange": 15,
      "verified": true,
      "serviceIDs": [
        3,
        4
      ],
      "bookingIDs": []
    }
  },
  {
    "userDetails": {
      "id": 5,
      "fname": "Eve",
      "sname": "White",
      "loginDetails": {
        "email": "eve@example.com",
        "username": "eve@example.com",
        "password": "password"
      }
    },
    "roles": [
      "petminder",
      "petowner"
    ],
    "currentRole": "petowner",
    "primaryUserInfo": {
      "profilePic": "",
      "dob": "1995-08-25T00:00:00.000Z",
      "location": {
        "name": "Nottingham",
        "longitude": -1.1517,
        "latitude": 52.9548
      },
      "suspended": false,
      "suspendReason": null,
      "suspendEndsAt": null
    },
    "ownerRoleInfo": {
      "petIDs": [
        1,
        2
      ],
      "bookingIDs": [
        1,
        2,
        3
      ]
    },
    "minderRoleInfo": {
      "rating": 0,
      "bio": "Pet owner and minder with a passion for animals, especially dogs!",
      "pictures": [
        "1",
        "2",
        "3"
      ],
      "availability": "Flexible",
      "distanceRange": 3,
      "verified": true,
      "serviceIDs": [
        5,
        6
      ],
      "bookingIDs": []
    }
  },
  {
    "userDetails": {
      "id": 6,
      "fname": "Mark",
      "sname": "Robert",
      "loginDetails": {
        "email": "mark@example.com",
        "username": "markR",
        "password": "password"
      }
    },
    "roles": [
      "petminder"
    ],
    "currentRole": "petminder",
    "primaryUserInfo": {
      "profilePic": "",
      "dob": "2000-05-03T00:00:00.000Z",
      "location": {
        "name": "",
        "longitude": 0,
        "latitude": 0
      },
      "suspended": false,
      "suspendReason": null,
      "suspendEndsAt": null
    },
    "ownerRoleInfo": {
      "petIDs": [],
      "bookingIDs": []
    },
    "minderRoleInfo": {
      "rating": 0,
      "bio": "",
      "pictures": [],
      "availability": "",
      "distanceRange": 0,
      "verified": false,
      "serviceIDs": [
        7,
        8
      ],
      "bookingIDs": []
    }
  }
]